{
  "sumber": "GALERI 24",
  "diperbarui": "Diperbarui Jumat, 3 April 2026",
  "waktu_scraping": "2026-04-03T21:26:36",
  "tanggal_hari_ini": "2026-04-03",
  "daftar_harga": [
    {
      "berat": "0.5",
      "harga_jual": "Rp1.505.000",
      "harga_buyback": "Rp1.346.000"
    },
    {
      "berat": "1",
      "harga_jual": "Rp2.870.000",
      "harga_buyback": "Rp2.692.000"
    },
    {
      "berat": "2",
      "harga_jual": "Rp5.672.000",
      "harga_buyback": "Rp5.385.000"
    },
    {
      "berat": "5",
      "harga_jual": "Rp14.076.000",
      "harga_buyback": "Rp13.463.000"
    },
    {
      "berat": "10",
      "harga_jual": "Rp28.076.000",
      "harga_buyback": "Rp26.927.000"
    },
    {
      "berat": "25",
      "harga_jual": "Rp69.812.000",
      "harga_buyback": "Rp66.989.000"
    },
    {
      "berat": "50",
      "harga_jual": "Rp139.514.000",
      "harga_buyback": "Rp133.979.000"
    },
    {
      "berat": "100",
      "harga_jual": "Rp278.891.000",
      "harga_buyback": "Rp267.959.000"
    },
    {
      "berat": "250",
      "harga_jual": "Rp695.513.000",
      "harga_buyback": "Rp666.599.000"
    },
    {
      "berat": "500",
      "harga_jual": "Rp1.391.025.000",
      "harga_buyback": "Rp1.333.198.000"
    },
    {
      "berat": "1000",
      "harga_jual": "Rp2.782.049.000",
      "harga_buyback": "Rp2.666.397.000"
    }
  ]
}